<?xml version="1.0" encoding="ISO-8859-1"?><P12><CUADROS BARAJA="true"><b_instrucciones ANCLADO="false" ALTO="39.95" ANCHO="725" Y="0" X="0" ALPHA="100" FONDO="false" FONDOCOLOR="16777215" BORDERCOLOR="13421772" BORDE="true" PATHIMAGEN="undefined" IMAGEN="false" /><b_centro ANCLADO="false" ALTO="374.45" ANCHO="616" Y="42" X="0.05" ALPHA="100" FONDO="false" FONDOCOLOR="16777215" BORDERCOLOR="13421772" BORDE="true" PATHIMAGEN="undefined" IMAGEN="false" /><b_barra ANCLADO="false" ALTO="39.95" ANCHO="725" Y="490" X="0" ALPHA="100" FONDO="false" FONDOCOLOR="15856113" BORDERCOLOR="13359580" BORDE="true" PATHIMAGEN="undefined" IMAGEN="false" /></CUADROS><ETIQUETAS><etiquetainstrucciones ALIGN="DEPRECATED" TAMANO="DEPRECATED" FUENTE="DEPRECATED" SUBRAYADO="DEPRECATED" NEGRITA="DEPRECATED" CURSIVA="DEPRECATED" COLOR="DEPRECATED" TEXTO="&lt;TEXTFORMAT LEADING=&quot;2&quot;&gt;&lt;P ALIGN=&quot;CENTER&quot;&gt;&lt;FONT FACE=&quot;Verdana&quot; SIZE=&quot;20&quot; COLOR=&quot;#000000&quot; LETTERSPACING=&quot;0&quot; KERNING=&quot;0&quot;&gt;&lt;B&gt;Empareja la imagen correspondiente con el texto&lt;/B&gt;&lt;/FONT&gt;&lt;/P&gt;&lt;/TEXTFORMAT&gt;" ANCLADO="false" ALTO="30" ANCHO="690" Y="-27" X="9" ALPHA="100" FONDO="false" FONDOCOLOR="16777215" BORDERCOLOR="13421772" BORDE="false" PATHIMAGEN="undefined" IMAGEN="false" AREA_COMANDOS_ACCESIBILIDAD="undefined" ALTERNATIVA="" /><titulo ALIGN="DEPRECATED" TAMANO="DEPRECATED" FUENTE="DEPRECATED" SUBRAYADO="DEPRECATED" NEGRITA="DEPRECATED" CURSIVA="DEPRECATED" COLOR="DEPRECATED" TEXTO="" ANCLADO="false" ALTO="14" ANCHO="725" Y="-25" X="0" ALPHA="100" FONDO="false" FONDOCOLOR="16777215" BORDERCOLOR="13421772" BORDE="false" PATHIMAGEN="undefined" IMAGEN="false" AREA_COMANDOS_ACCESIBILIDAD="undefined" ALTERNATIVA="" /></ETIQUETAS><BOTONES><botonLimpiar ALIGN="DEPRECATED" TAMANO="DEPRECATED" FUENTE="DEPRECATED" SUBRAYADO="DEPRECATED" NEGRITA="DEPRECATED" CURSIVA="DEPRECATED" COLOR="DEPRECATED" TEXTO="&lt;TEXTFORMAT LEADING=&quot;2&quot;&gt;&lt;P ALIGN=&quot;CENTER&quot;&gt;&lt;FONT FACE=&quot;Verdana&quot; SIZE=&quot;11&quot; COLOR=&quot;#000000&quot; LETTERSPACING=&quot;0&quot; KERNING=&quot;0&quot;&gt;Borrar &lt;/FONT&gt;&lt;/P&gt;&lt;/TEXTFORMAT&gt;" ANCLADO="false" ALTO="25" ANCHO="65" Y="498" X="255.5" ALPHA="100" FONDO="false" FONDOCOLOR="16777215" BORDERCOLOR="11711154" BORDE="true" PATHIMAGEN="undefined" IMAGEN="false" AREA_COMANDOS_ACCESIBILIDAD="false" ALTERNATIVA="" /><botonVerificar ALIGN="DEPRECATED" TAMANO="DEPRECATED" FUENTE="DEPRECATED" SUBRAYADO="DEPRECATED" NEGRITA="DEPRECATED" CURSIVA="DEPRECATED" COLOR="DEPRECATED" TEXTO="&lt;TEXTFORMAT LEADING=&quot;2&quot;&gt;&lt;P ALIGN=&quot;CENTER&quot;&gt;&lt;FONT FACE=&quot;Verdana&quot; SIZE=&quot;11&quot; COLOR=&quot;#000000&quot; LETTERSPACING=&quot;0&quot; KERNING=&quot;0&quot;&gt;Comprobar &lt;/FONT&gt;&lt;/P&gt;&lt;/TEXTFORMAT&gt;" ANCLADO="false" ALTO="25" ANCHO="80" Y="497" X="335.6" ALPHA="100" FONDO="false" FONDOCOLOR="16777215" BORDERCOLOR="11711154" BORDE="true" PATHIMAGEN="undefined" IMAGEN="false" AREA_COMANDOS_ACCESIBILIDAD="false" ALTERNATIVA="" /><botonSolucion ALIGN="DEPRECATED" TAMANO="DEPRECATED" FUENTE="DEPRECATED" SUBRAYADO="DEPRECATED" NEGRITA="DEPRECATED" CURSIVA="DEPRECATED" COLOR="DEPRECATED" TEXTO="&lt;TEXTFORMAT LEADING=&quot;2&quot;&gt;&lt;P ALIGN=&quot;CENTER&quot;&gt;&lt;FONT FACE=&quot;Verdana&quot; SIZE=&quot;11&quot; COLOR=&quot;#000000&quot; LETTERSPACING=&quot;0&quot; KERNING=&quot;0&quot;&gt;Terminar &lt;/FONT&gt;&lt;/P&gt;&lt;/TEXTFORMAT&gt;" ANCLADO="false" ALTO="25" ANCHO="70" Y="497" X="426.75" ALPHA="100" FONDO="false" FONDOCOLOR="16777215" BORDERCOLOR="11711154" BORDE="true" PATHIMAGEN="undefined" IMAGEN="false" AREA_COMANDOS_ACCESIBILIDAD="false" ALTERNATIVA="" /><botonExplicacionSolucion /></BOTONES><PATHMEDIA TIPORESPUESTAS="textos" TIPOPREGUNTAS="-1"><PATH0 ALTERNATIVA_RESPUESTA="" ALTERNATIVA_PREGUNTA="" RESPUESTA="TECLADO" PREGUNTA="imagenes/teclado_Mesadetrabajo1.jpg" /><PATH1 ALTERNATIVA_RESPUESTA="" ALTERNATIVA_PREGUNTA="" RESPUESTA="TORRE" PREGUNTA="imagenes/torre_Mesadetrabajo1.jpg" /><PATH2 ALTERNATIVA_RESPUESTA="" ALTERNATIVA_PREGUNTA="" RESPUESTA="MOUSE" PREGUNTA="imagenes/mouse_Mesadetrabajo1.jpg" /><PATH3 ALTERNATIVA_RESPUESTA="" ALTERNATIVA_PREGUNTA="" RESPUESTA="PANTALLA" PREGUNTA="imagenes/pantalla_Mesadetrabajo1.jpg" /></PATHMEDIA><ELEMENTOMEDIA ALTERNATIVA_GEN="undefined" ALTERNATIVA_ESP="undefined" ALTERNATIVA_SEL="undefined" ALTERNATIVA_RESP="undefined" ALTERNATIVA_PREG="undefined"><ELEMENTO0><PREGUNTA BORDE="false" ALTO="100" ANCHO="100" Y="38" X="65.05" /><RESPUESTA ALIGN="CENTER" TAMANO="12" FUENTE="Verdana" SUBRAYADO="false" NEGRITA="true" CURSIVA="false" COLOR="16777215" TEXTO="TECLADO" ANCLADO="false" ALTO="20" ANCHO="175" Y="379" X="392" ALPHA="100" FONDO="true" FONDOCOLOR="10027008" BORDERCOLOR="16777215" BORDE="true" PATHIMAGEN="undefined" AREA_COMANDOS_ACCESIBILIDAD="undefined" IMAGEN="false" /><FLECHA Y="87" X="189" /></ELEMENTO0><ELEMENTO1><PREGUNTA BORDE="false" ALTO="100" ANCHO="100" Y="123" X="58" /><RESPUESTA ALIGN="CENTER" TAMANO="12" FUENTE="Verdana" SUBRAYADO="false" NEGRITA="true" CURSIVA="false" COLOR="16777215" TEXTO="TORRE" ANCLADO="false" ALTO="21" ANCHO="180" Y="278" X="398" ALPHA="100" FONDO="true" FONDOCOLOR="10027008" BORDERCOLOR="16777215" BORDE="true" PATHIMAGEN="undefined" AREA_COMANDOS_ACCESIBILIDAD="undefined" IMAGEN="false" /><FLECHA Y="185" X="188" /></ELEMENTO1><ELEMENTO2><PREGUNTA BORDE="false" ALTO="100" ANCHO="100" Y="225" X="51" /><RESPUESTA ALIGN="CENTER" TAMANO="12" FUENTE="Verdana" SUBRAYADO="false" NEGRITA="true" CURSIVA="false" COLOR="16777215" TEXTO="MOUSE" ANCLADO="false" ALTO="20" ANCHO="175" Y="174" X="396" ALPHA="100" FONDO="true" FONDOCOLOR="10027008" BORDERCOLOR="16777215" BORDE="true" PATHIMAGEN="undefined" AREA_COMANDOS_ACCESIBILIDAD="undefined" IMAGEN="false" /><FLECHA Y="280" X="186" /></ELEMENTO2><ELEMENTO3><PREGUNTA BORDE="false" ALTO="100" ANCHO="100" Y="328" X="62" /><RESPUESTA ALIGN="CENTER" TAMANO="12" FUENTE="Verdana" SUBRAYADO="false" NEGRITA="true" CURSIVA="false" COLOR="16777215" TEXTO="PANTALLA" ANCLADO="false" ALTO="20" ANCHO="175" Y="94" X="395" ALPHA="100" FONDO="true" FONDOCOLOR="10027008" BORDERCOLOR="16777215" BORDE="true" PATHIMAGEN="undefined" AREA_COMANDOS_ACCESIBILIDAD="undefined" IMAGEN="false" /><FLECHA Y="376" X="186" /></ELEMENTO3></ELEMENTOMEDIA><RETROALIMENTACION MAX_INTENTOS="-1" LIMITE_INTENTOS="false" PUNTUACION="100" SOLUCIONEXPLICACION="" INTENTOS_ACTIVAR_FINALIZAR="-1"><ACIERTO ANIMACION="" SONIDO="sonidos/Efectodesonidobienwinganadoracierto.mp3" TEXTO="Muy bien!" /><INTENTOSAGOTADOS ANIMACION="" SONIDO="sonidos/Falla_Fallo.ChisteMalo_EfectodeSonido.mp3" TEXTO="Intntalo otra vez!" /><TIEMPOS ANIMACION="" SONIDO="sonidos/Falla_Fallo.ChisteMalo_EfectodeSonido.mp3" TEXTO="Se ha agotado el tiempo!" TIEMPO="-1" /></RETROALIMENTACION><ITINERARIOS ETIQUETA_FOTOGRAMA_MAYOR="Frame2" ETIQUETA_FOTOGRAMA_IGUAL="Frame2" ETIQUETA_FOTOGRAMA_MENOR="Frame2" MINIMA="-1" /><CRUCETA ALTO="0" ANCHO="0" y="-2.85" x="-2.85" /><ATRIBUTOS EXPLICACION_GENERAL="" EXPLICACION_ESPECIFICA="" VOCABULARIO_SELECCIONADO="" /></P12>